mcrender_block-0.1.2.dist-info/licenses/LICENSE
vibecoded_mc_renderer/__init__.py
vibecoded_mc_renderer/__main__.py
vibecoded_mc_renderer/cli.py
vibecoded_mc_renderer/core/__init__.py
vibecoded_mc_renderer/core/forge_blockstate_loader.py
vibecoded_mc_renderer/core/gregtech_analyzer.py
vibecoded_mc_renderer/core/model_loader.py
vibecoded_mc_renderer/core/renderer.py
vibecoded_mc_renderer/core/resource_manager.py
vibecoded_mc_renderer/core/texture_manager.py
vibecoded_mc_renderer/models/__init__.py
vibecoded_mc_renderer/rendering/__init__.py
vibecoded_mc_renderer/rendering/isometric.py
vibecoded_mc_renderer/rendering/layers.py
vibecoded_mc_renderer/rendering/machine_renderer.py
vibecoded_mc_renderer/rendering/renderer_3d.py
vibecoded_mc_renderer/utils/__init__.py
vibecoded_mc_renderer/utils/colors.py
vibecoded_mc_renderer/utils/materials.py
mcrender_block-0.1.2.dist-info/METADATA
mcrender_block-0.1.2.dist-info/WHEEL
mcrender_block-0.1.2.dist-info/entry_points.txt
mcrender_block-0.1.2.dist-info/top_level.txt
mcrender_block-0.1.2.dist-info/RECORD
