Metadata-Version: 2.4
Name: mcrender-block
Version: 0.1.2
Summary: CLI tool for rendering Minecraft blocks from jar files
Author: almajd3713
License: MIT
Project-URL: Homepage, https://github.com/almajd3713/vibecoded_mc_renderer
Project-URL: Repository, https://github.com/almajd3713/vibecoded_mc_renderer
Project-URL: Issues, https://github.com/almajd3713/vibecoded_mc_renderer/issues
Keywords: minecraft,renderer,isometric,gregtech,modded,cli
Classifier: Development Status :: 4 - Beta
Classifier: Environment :: Console
Classifier: Intended Audience :: Developers
Classifier: Intended Audience :: End Users/Desktop
Classifier: License :: OSI Approved :: MIT License
Classifier: Operating System :: OS Independent
Classifier: Programming Language :: Python :: 3
Classifier: Programming Language :: Python :: 3.10
Classifier: Programming Language :: Python :: 3.11
Classifier: Programming Language :: Python :: 3.12
Classifier: Topic :: Games/Entertainment
Classifier: Topic :: Multimedia :: Graphics
Classifier: Topic :: Software Development :: Libraries :: Python Modules
Requires-Python: >=3.10
License-File: LICENSE
Requires-Dist: Pillow>=9.0.0
Requires-Dist: typer>=0.9.0
Requires-Dist: rich>=13.0.0
Requires-Dist: numpy>=1.20.0
Requires-Dist: moderngl>=5.6.0
Requires-Dist: pyrr>=0.10.0
Provides-Extra: dev
Requires-Dist: pytest>=7.0.0; extra == "dev"
Requires-Dist: pytest-cov>=4.0.0; extra == "dev"
Requires-Dist: black>=22.0.0; extra == "dev"
Requires-Dist: mypy>=0.990; extra == "dev"
Requires-Dist: ruff>=0.0.260; extra == "dev"
Dynamic: license-file
